tube_stat/__init__.py
tube_stat/cli.py
tube_stat-0.1.3.dist-info/METADATA
tube_stat-0.1.3.dist-info/WHEEL
tube_stat-0.1.3.dist-info/entry_points.txt
tube_stat-0.1.3.dist-info/RECORD
