Metadata-Version: 2.3
Name: tube-stat
Version: 0.1.3
Summary: 
Author: JJ
Author-email: nicetry@noemail.com
Requires-Python: >=3.13
Classifier: Programming Language :: Python :: 3
Classifier: Programming Language :: Python :: 3.13
Requires-Dist: click (>=8.1.8,<9.0.0)
Requires-Dist: requests (>=2.32.3,<3.0.0)
